setup.py
src/digimat/__init__.py
src/digimat.ipcamera.egg-info/PKG-INFO
src/digimat.ipcamera.egg-info/SOURCES.txt
src/digimat.ipcamera.egg-info/dependency_links.txt
src/digimat.ipcamera.egg-info/namespace_packages.txt
src/digimat.ipcamera.egg-info/not-zip-safe
src/digimat.ipcamera.egg-info/requires.txt
src/digimat.ipcamera.egg-info/top_level.txt
src/digimat/ipcamera/__init__.py
src/digimat/ipcamera/ipcamera.py