Metadata-Version: 1.0
Name: digimat.ipcamera
Version: 0.1.4
Summary: Digimat IP Camera
Home-page: http://www.digimat.ch
Author: Frederic Hess
Author-email: fhess@splust.ch
License: PSF
Platform: UNKNOWN
